data/bbc_full_articles.txt
data/bbc_sample_corpus.txt
data/ebc_articles.txt
data/embeddings.bin
data/merged_large_corpus.txt
data/sample_corpus.txt
data/stopwords.txt
data/wikipedia_full_corpus.txt
nlpta/__init__.py
nlpta/cleaning.py
nlpta/datasets.py
nlpta/embeddings.py
nlpta/stopwords.py
nlpta/tokenization.py
nlpta/__pycache__/__init__.cpython-312.pyc
nlpta/__pycache__/cleaning.cpython-312.pyc
nlpta/__pycache__/datasets.cpython-312.pyc
nlpta/__pycache__/embeddings.cpython-312.pyc
nlpta/__pycache__/stopwords.cpython-312.pyc
nlpta/__pycache__/tokenization.cpython-312.pyc
nlpta-0.1.0.dist-info/licenses/LICENSE
tests/__init__.py
tests/test_cleaning.py
tests/test_datasets.py
tests/test_embeddings.py
tests/test_stopwords.py
tests/test_tokenization.py
nlpta-0.1.0.dist-info/METADATA
nlpta-0.1.0.dist-info/WHEEL
nlpta-0.1.0.dist-info/top_level.txt
nlpta-0.1.0.dist-info/RECORD
